README.md
setup.py
micropython_tziot.egg-info/PKG-INFO
micropython_tziot.egg-info/SOURCES.txt
micropython_tziot.egg-info/dependency_links.txt
micropython_tziot.egg-info/top_level.txt
tziot/__init__.py
tziot/apply.py
tziot/config.py
tziot/conn.py
tziot/fdcom.py
tziot/fpipe.py
tziot/param.py
tziot/parsecmp.py
tziot/standardlayer.py
tziot/tziot.py