Metadata-Version: 2.1
Name: micropython-tziot
Version: 1.3
Summary: tziot sdk for micropython
Home-page: https://github.com/jdhxyy/tziot-micropython
Author: jdh99
Author-email: jdh821@163.com
License: UNKNOWN
Platform: UNKNOWN
